[{"date":"2020-10-28T00:40:58.959Z","success":true,"statusCode":200},{"date":"2020-10-28T01:30:46.120Z","success":true,"statusCode":200},{"date":"2020-10-28T02:04:56.454Z","success":true,"statusCode":200},{"date":"2020-10-28T02:34:14.767Z","success":true,"statusCode":200},{"date":"2020-10-28T02:47:19.118Z","success":true,"statusCode":200},{"date":"2020-10-28T02:54:53.801Z","success":true,"statusCode":200},{"date":"2020-10-28T03:14:31.987Z","success":true,"statusCode":200},{"date":"2020-10-28T03:34:12.284Z","success":true,"statusCode":200},{"date":"2020-10-28T03:47:54.305Z","success":true,"statusCode":200},{"date":"2020-10-28T03:55:25.172Z","success":true,"statusCode":200},{"date":"2020-10-28T04:18:44.165Z","success":true,"statusCode":200},{"date":"2020-10-28T04:40:28.888Z","success":true,"statusCode":200},{"date":"2020-10-28T04:53:31.983Z","success":true,"statusCode":200},{"date":"2020-10-28T05:14:07.702Z","success":true,"statusCode":200},{"date":"2020-10-28T05:32:32.140Z","success":true,"statusCode":200},{"date":"2020-10-28T05:44:40.165Z","success":true,"statusCode":200},{"date":"2020-10-28T05:52:40.414Z","success":true,"statusCode":200},{"date":"2020-10-28T06:16:12.774Z","success":true,"statusCode":200},{"date":"2020-10-28T06:37:50.092Z","success":true,"statusCode":200},{"date":"2020-10-28T06:52:07.329Z","success":true,"statusCode":200},{"date":"2020-10-28T07:15:31.620Z","success":true,"statusCode":200},{"date":"2020-10-28T07:34:11.966Z","success":true,"statusCode":200},{"date":"2020-10-28T07:45:10.721Z","success":true,"statusCode":200},{"date":"2020-10-28T07:52:38.747Z","success":true,"statusCode":200},{"date":"2020-10-28T08:16:44.733Z","success":true,"statusCode":200},{"date":"2020-10-28T08:37:19.400Z","success":true,"statusCode":200},{"date":"2020-10-28T08:48:36.068Z","success":true,"statusCode":200},{"date":"2020-10-28T08:55:49.587Z","success":true,"statusCode":200}]