[{"date":"2020-11-02T00:24:47.323Z","success":true,"statusCode":200},{"date":"2020-11-02T00:52:48.162Z","success":true,"statusCode":200},{"date":"2020-11-02T01:10:48.048Z","success":true,"statusCode":200},{"date":"2020-11-02T01:24:45.118Z","success":true,"statusCode":200},{"date":"2020-11-02T01:34:03.151Z","success":true,"statusCode":200},{"date":"2020-11-02T01:42:44.219Z","success":true,"statusCode":200},{"date":"2020-11-02T01:52:34.454Z","success":true,"statusCode":200},{"date":"2020-11-02T02:10:42.405Z","success":true,"statusCode":200},{"date":"2020-11-02T02:23:03.060Z","success":true,"statusCode":200},{"date":"2020-11-02T02:33:39.003Z","success":true,"statusCode":200},{"date":"2020-11-02T02:42:43.292Z","success":true,"statusCode":200},{"date":"2020-11-02T02:52:53.160Z","success":true,"statusCode":200},{"date":"2020-11-02T03:08:45.181Z","success":true,"statusCode":200},{"date":"2020-11-02T03:18:20.368Z","success":true,"statusCode":200}]