[{"date":"2021-04-18T01:17:20.191Z","success":true,"statusCode":200},{"date":"2021-04-18T02:25:36.305Z","success":true,"statusCode":200},{"date":"2021-04-18T02:59:44.635Z","success":true,"statusCode":200},{"date":"2021-04-18T03:33:06.367Z","success":true,"statusCode":200},{"date":"2021-04-18T03:56:10.019Z","success":true,"statusCode":200},{"date":"2021-04-18T04:27:03.701Z","success":true,"statusCode":200},{"date":"2021-04-18T04:53:59.950Z","success":true,"statusCode":200},{"date":"2021-04-18T05:19:50.160Z","success":true,"statusCode":200},{"date":"2021-04-18T05:41:27.380Z","success":true,"statusCode":200},{"date":"2021-04-18T05:54:12.069Z","success":true,"statusCode":200},{"date":"2021-04-18T06:20:07.320Z","success":true,"statusCode":200},{"date":"2021-04-18T06:47:07.352Z","success":true,"statusCode":200},{"date":"2021-04-18T07:04:29.423Z","success":true,"statusCode":200},{"date":"2021-04-18T07:30:17.673Z","success":true,"statusCode":200},{"date":"2021-04-18T07:48:29.690Z","success":true,"statusCode":200},{"date":"2021-04-18T07:55:49.966Z","success":true,"statusCode":200},{"date":"2021-04-18T08:22:34.264Z","success":true,"statusCode":200},{"date":"2021-04-18T08:46:16.012Z","success":true,"statusCode":200},{"date":"2021-04-18T08:57:41.069Z","success":true,"statusCode":200},{"date":"2021-04-18T09:27:28.822Z","success":true,"statusCode":200},{"date":"2021-04-18T09:48:29.714Z","success":true,"statusCode":200},{"date":"2021-04-18T09:58:02.757Z","success":true,"statusCode":200},{"date":"2021-04-18T10:27:17.389Z","success":true,"statusCode":200},{"date":"2021-04-18T10:46:07.396Z","success":true,"statusCode":200},{"date":"2021-04-18T10:56:37.746Z","success":true,"statusCode":200},{"date":"2021-04-18T11:19:36.126Z","success":true,"statusCode":200},{"date":"2021-04-18T11:35:13.632Z","success":true,"statusCode":200},{"date":"2021-04-18T11:46:38.840Z","success":true,"statusCode":200},{"date":"2021-04-18T11:54:08.255Z","success":true,"statusCode":200},{"date":"2021-04-18T12:23:44.018Z","success":true,"statusCode":200},{"date":"2021-04-18T12:58:19.798Z","success":true,"statusCode":200},{"date":"2021-04-18T13:29:46.785Z","success":true,"statusCode":200},{"date":"2021-04-18T13:47:51.946Z","success":true,"statusCode":200},{"date":"2021-04-18T13:55:17.186Z","success":true,"statusCode":200},{"date":"2021-04-18T14:15:56.995Z","success":true,"statusCode":200},{"date":"2021-04-18T14:33:48.691Z","success":true,"statusCode":200},{"date":"2021-04-18T14:47:14.619Z","success":true,"statusCode":200},{"date":"2021-04-18T14:54:34.629Z","success":true,"statusCode":200},{"date":"2021-04-18T15:16:48.024Z","success":true,"statusCode":200},{"date":"2021-04-18T15:41:59.817Z","success":true,"statusCode":200},{"date":"2021-04-18T15:59:51.153Z","success":true,"statusCode":200},{"date":"2021-04-18T16:50:00.773Z","success":true,"statusCode":200},{"date":"2021-04-18T17:28:26.463Z","success":true,"statusCode":200},{"date":"2021-04-18T18:02:01.401Z","success":true,"statusCode":200},{"date":"2021-04-18T18:40:18.921Z","success":true,"statusCode":200},{"date":"2021-04-18T19:03:48.502Z","success":true,"statusCode":200},{"date":"2021-04-18T19:25:27.874Z","success":true,"statusCode":200},{"date":"2021-04-18T19:37:59.152Z","success":true,"statusCode":200},{"date":"2021-04-18T19:45:28.872Z","success":true,"statusCode":200}]