[{"date":"2021-03-05T00:32:58.776Z","success":true,"statusCode":200},{"date":"2021-03-05T01:28:18.463Z","success":true,"statusCode":200},{"date":"2021-03-05T02:11:31.183Z","success":true,"statusCode":200},{"date":"2021-03-05T02:44:54.370Z","success":true,"statusCode":200},{"date":"2021-03-05T02:57:34.810Z","success":true,"statusCode":200},{"date":"2021-03-05T03:25:10.172Z","success":true,"statusCode":200},{"date":"2021-03-05T03:42:49.321Z","success":true,"statusCode":200},{"date":"2021-03-05T03:55:17.074Z","success":true,"statusCode":200},{"date":"2021-03-05T04:16:25.783Z","success":true,"statusCode":200},{"date":"2021-03-05T04:43:10.186Z","success":true,"statusCode":200},{"date":"2021-03-05T04:58:23.154Z","success":true,"statusCode":200},{"date":"2021-03-05T05:23:36.869Z","success":true,"statusCode":200},{"date":"2021-03-05T05:40:35.403Z","success":true,"statusCode":200},{"date":"2021-03-05T05:52:50.708Z","success":true,"statusCode":200},{"date":"2021-03-05T06:14:30.456Z","success":true,"statusCode":200},{"date":"2021-03-05T06:39:31.248Z","success":true,"statusCode":200},{"date":"2021-03-05T06:56:34.003Z","success":true,"statusCode":200},{"date":"2021-03-05T07:19:25.935Z","success":true,"statusCode":200},{"date":"2021-03-05T07:34:15.432Z","success":true,"statusCode":200},{"date":"2021-03-05T07:46:09.505Z","success":true,"statusCode":200},{"date":"2021-03-05T07:53:37.809Z","success":true,"statusCode":200},{"date":"2021-03-05T08:41:41.179Z","success":true,"statusCode":200},{"date":"2021-03-05T08:56:47.468Z","success":true,"statusCode":200},{"date":"2021-03-05T09:22:58.144Z","success":true,"statusCode":200},{"date":"2021-03-05T09:42:45.657Z","success":true,"statusCode":200},{"date":"2021-03-05T09:55:11.763Z","success":true,"statusCode":200},{"date":"2021-03-05T10:15:19.900Z","success":true,"statusCode":200},{"date":"2021-03-05T10:37:53.018Z","success":true,"statusCode":200},{"date":"2021-03-05T10:53:03.830Z","success":true,"statusCode":200},{"date":"2021-03-05T11:12:38.037Z","success":true,"statusCode":200},{"date":"2021-03-05T11:32:32.931Z","success":true,"statusCode":200},{"date":"2021-03-05T11:45:48.057Z","success":true,"statusCode":200},{"date":"2021-03-05T11:53:13.541Z","success":true,"statusCode":200},{"date":"2021-03-05T12:17:25.126Z","success":true,"statusCode":200},{"date":"2021-03-05T12:47:27.989Z","success":true,"statusCode":200},{"date":"2021-03-05T13:03:22.072Z","success":true,"statusCode":200},{"date":"2021-03-05T13:28:20.712Z","success":true,"statusCode":200},{"date":"2021-03-05T13:43:37.514Z","success":true,"statusCode":200},{"date":"2021-03-05T13:52:43.357Z","success":true,"statusCode":200},{"date":"2021-03-05T14:13:19.422Z","success":true,"statusCode":200},{"date":"2021-03-05T14:33:33.844Z","success":true,"statusCode":200},{"date":"2021-03-05T14:47:15.605Z","success":true,"statusCode":200},{"date":"2021-03-05T14:54:33.047Z","success":true,"statusCode":200},{"date":"2021-03-05T15:13:01.987Z","success":true,"statusCode":200},{"date":"2021-03-05T15:35:21.492Z","success":false,"statusCode":404},{"date":"2021-03-05T15:51:22.262Z","success":true,"statusCode":200},{"date":"2021-03-05T16:21:13.256Z","success":true,"statusCode":200},{"date":"2021-03-05T17:11:27.784Z","success":true,"statusCode":200},{"date":"2021-03-05T17:47:08.248Z","success":true,"statusCode":200},{"date":"2021-03-05T18:00:10.487Z","success":true,"statusCode":200},{"date":"2021-03-05T18:28:44.530Z","success":true,"statusCode":200},{"date":"2021-03-05T18:53:15.634Z","success":true,"statusCode":200},{"date":"2021-03-05T19:09:32.815Z","success":true,"statusCode":200},{"date":"2021-03-05T19:24:09.291Z","success":true,"statusCode":200},{"date":"2021-03-05T19:35:55.876Z","success":true,"statusCode":200},{"date":"2021-03-05T19:43:51.052Z","success":true,"statusCode":200},{"date":"2021-03-05T19:52:39.157Z","success":true,"statusCode":200},{"date":"2021-03-05T20:13:35.314Z","success":true,"statusCode":200},{"date":"2021-03-05T20:34:43.279Z","success":true,"statusCode":200},{"date":"2021-03-05T20:46:58.931Z","success":true,"statusCode":200},{"date":"2021-03-05T20:54:23.503Z","success":true,"statusCode":200},{"date":"2021-03-05T21:11:52.662Z","success":true,"statusCode":200}]