[{"date":"2021-03-23T00:34:03.047Z","success":true,"statusCode":200},{"date":"2021-03-23T01:32:54.718Z","success":true,"statusCode":200},{"date":"2021-03-23T02:20:24.256Z","success":true,"statusCode":200},{"date":"2021-03-23T02:57:02.055Z","success":true,"statusCode":200},{"date":"2021-03-23T03:26:52.647Z","success":true,"statusCode":200},{"date":"2021-03-23T03:49:25.262Z","success":true,"statusCode":200},{"date":"2021-03-23T03:58:45.364Z","success":true,"statusCode":200},{"date":"2021-03-23T04:32:05.336Z","success":true,"statusCode":200},{"date":"2021-03-23T04:58:34.853Z","success":true,"statusCode":200},{"date":"2021-03-23T05:26:38.025Z","success":true,"statusCode":200},{"date":"2021-03-23T05:46:55.878Z","success":false,"statusCode":429}]