[{"date":"2021-07-30T00:44:29.075Z","success":true,"statusCode":200},{"date":"2021-07-30T01:51:54.040Z","success":true,"statusCode":200},{"date":"2021-07-30T02:29:05.156Z","success":true,"statusCode":200},{"date":"2021-07-30T02:50:25.431Z","success":true,"statusCode":200},{"date":"2021-07-30T03:14:39.045Z","success":true,"statusCode":200},{"date":"2021-07-30T03:35:08.464Z","success":true,"statusCode":200},{"date":"2021-07-30T03:48:16.411Z","success":true,"statusCode":200},{"date":"2021-07-30T03:58:05.503Z","success":true,"statusCode":200},{"date":"2021-07-30T04:26:41.811Z","success":true,"statusCode":200},{"date":"2021-07-30T04:50:49.021Z","success":true,"statusCode":200},{"date":"2021-07-30T05:11:17.326Z","success":true,"statusCode":200},{"date":"2021-07-30T05:27:48.886Z","success":true,"statusCode":200},{"date":"2021-07-30T05:37:25.488Z","success":true,"statusCode":200},{"date":"2021-07-30T05:47:06.945Z","success":true,"statusCode":200},{"date":"2021-07-30T05:57:00.803Z","success":true,"statusCode":200}]