[{"date":"2021-07-13T00:55:58.680Z","success":true,"statusCode":200},{"date":"2021-07-13T01:59:34.456Z","success":true,"statusCode":200},{"date":"2021-07-13T02:31:49.538Z","success":true,"statusCode":200},{"date":"2021-07-13T02:49:19.916Z","success":true,"statusCode":200},{"date":"2021-07-13T02:58:59.666Z","success":true,"statusCode":200},{"date":"2021-07-13T03:25:05.502Z","success":true,"statusCode":200},{"date":"2021-07-13T03:41:57.377Z","success":true,"statusCode":200},{"date":"2021-07-13T03:54:56.025Z","success":true,"statusCode":200},{"date":"2021-07-13T04:16:37.780Z","success":true,"statusCode":200},{"date":"2021-07-13T04:42:42.484Z","success":true,"statusCode":200},{"date":"2021-07-13T04:57:42.140Z","success":true,"statusCode":200},{"date":"2021-07-13T05:16:30.323Z","success":true,"statusCode":200},{"date":"2021-07-13T05:28:09.849Z","success":true,"statusCode":200},{"date":"2021-07-13T05:37:53.416Z","success":false,"statusCode":429},{"date":"2021-07-13T05:47:44.479Z","success":true,"statusCode":200},{"date":"2021-07-13T05:57:34.271Z","success":true,"statusCode":200},{"date":"2021-07-13T06:24:04.594Z","success":true,"statusCode":200},{"date":"2021-07-13T06:48:54.874Z","success":true,"statusCode":200},{"date":"2021-07-13T06:58:33.477Z","success":true,"statusCode":200},{"date":"2021-07-13T07:18:59.799Z","success":true,"statusCode":200},{"date":"2021-07-13T07:29:56.009Z","success":true,"statusCode":200},{"date":"2021-07-13T07:39:35.078Z","success":true,"statusCode":200},{"date":"2021-07-13T07:49:35.075Z","success":true,"statusCode":200},{"date":"2021-07-13T07:59:21.654Z","success":true,"statusCode":200},{"date":"2021-07-13T08:24:39.924Z","success":true,"statusCode":200},{"date":"2021-07-13T08:40:11.587Z","success":true,"statusCode":200},{"date":"2021-07-13T08:49:42.739Z","success":true,"statusCode":200},{"date":"2021-07-13T08:59:23.260Z","success":true,"statusCode":200},{"date":"2021-07-13T09:23:55.503Z","success":true,"statusCode":200},{"date":"2021-07-13T09:41:33.952Z","success":true,"statusCode":200},{"date":"2021-07-13T09:54:48.803Z","success":true,"statusCode":200},{"date":"2021-07-13T10:14:19.006Z","success":true,"statusCode":200},{"date":"2021-07-13T10:34:59.770Z","success":true,"statusCode":200},{"date":"2021-07-13T10:46:21.388Z","success":true,"statusCode":200},{"date":"2021-07-13T10:55:58.993Z","success":true,"statusCode":200},{"date":"2021-07-13T11:12:13.275Z","success":true,"statusCode":200},{"date":"2021-07-13T11:27:04.357Z","success":true,"statusCode":200},{"date":"2021-07-13T11:36:48.158Z","success":true,"statusCode":200},{"date":"2021-07-13T11:46:32.259Z","success":true,"statusCode":200},{"date":"2021-07-13T11:56:08.900Z","success":true,"statusCode":200},{"date":"2021-07-13T12:25:57.292Z","success":true,"statusCode":200},{"date":"2021-07-13T13:01:43.165Z","success":true,"statusCode":200},{"date":"2021-07-13T13:29:54.615Z","success":true,"statusCode":200},{"date":"2021-07-13T13:44:31.588Z","success":true,"statusCode":200},{"date":"2021-07-13T13:54:48.287Z","success":true,"statusCode":200},{"date":"2021-07-13T14:11:41.730Z","success":true,"statusCode":200},{"date":"2021-07-13T14:28:07.901Z","success":true,"statusCode":200},{"date":"2021-07-13T14:38:06.536Z","success":true,"statusCode":200},{"date":"2021-07-13T14:47:57.652Z","success":true,"statusCode":200},{"date":"2021-07-13T14:57:47.083Z","success":true,"statusCode":200},{"date":"2021-07-13T15:23:26.897Z","success":true,"statusCode":200},{"date":"2021-07-13T15:45:57.009Z","success":true,"statusCode":200},{"date":"2021-07-13T15:56:21.427Z","success":true,"statusCode":200},{"date":"2021-07-13T16:25:16.606Z","success":true,"statusCode":200},{"date":"2021-07-13T17:02:01.617Z","success":true,"statusCode":200},{"date":"2021-07-13T17:31:09.085Z","success":true,"statusCode":200},{"date":"2021-07-13T17:47:12.583Z","success":true,"statusCode":200},{"date":"2021-07-13T17:56:52.339Z","success":true,"statusCode":200},{"date":"2021-07-13T18:21:01.107Z","success":true,"statusCode":200},{"date":"2021-07-13T18:46:26.469Z","success":true,"statusCode":200},{"date":"2021-07-13T18:55:59.731Z","success":true,"statusCode":200},{"date":"2021-07-13T19:11:49.131Z","success":true,"statusCode":200},{"date":"2021-07-13T19:24:48.118Z","success":true,"statusCode":200},{"date":"2021-07-13T19:35:12.729Z","success":true,"statusCode":200},{"date":"2021-07-13T19:44:55.649Z","success":true,"statusCode":200},{"date":"2021-07-13T19:54:49.900Z","success":true,"statusCode":200},{"date":"2021-07-13T20:13:11.100Z","success":true,"statusCode":200},{"date":"2021-07-13T20:31:03.529Z","success":true,"statusCode":200},{"date":"2021-07-13T20:45:00.222Z","success":true,"statusCode":200},{"date":"2021-07-13T20:54:56.863Z","success":true,"statusCode":200},{"date":"2021-07-13T21:12:22.116Z","success":true,"statusCode":200},{"date":"2021-07-13T21:32:30.720Z","success":true,"statusCode":200},{"date":"2021-07-13T21:45:12.565Z","success":true,"statusCode":200},{"date":"2021-07-13T21:54:48.593Z","success":true,"statusCode":200},{"date":"2021-07-13T22:12:44.018Z","success":true,"statusCode":200},{"date":"2021-07-13T22:32:34.689Z","success":true,"statusCode":200},{"date":"2021-07-13T22:44:48.381Z","success":true,"statusCode":200},{"date":"2021-07-13T22:55:02.800Z","success":true,"statusCode":200},{"date":"2021-07-13T23:12:52.879Z","success":true,"statusCode":200},{"date":"2021-07-13T23:30:30.543Z","success":true,"statusCode":200},{"date":"2021-07-13T23:45:13.651Z","success":true,"statusCode":200},{"date":"2021-07-13T23:55:15.664Z","success":true,"statusCode":200}]