[{"date":"2021-07-01T00:45:27.956Z","success":true,"statusCode":200},{"date":"2021-07-01T01:47:08.170Z","success":true,"statusCode":200},{"date":"2021-07-01T02:17:42.716Z","success":true,"statusCode":200},{"date":"2021-07-01T02:42:27.511Z","success":true,"statusCode":200},{"date":"2021-07-01T02:54:52.332Z","success":true,"statusCode":200},{"date":"2021-07-01T03:14:56.321Z","success":true,"statusCode":200},{"date":"2021-07-01T03:35:53.133Z","success":true,"statusCode":200},{"date":"2021-07-01T03:49:06.288Z","success":true,"statusCode":200},{"date":"2021-07-01T03:58:55.015Z","success":true,"statusCode":200},{"date":"2021-07-01T04:31:07.945Z","success":false,"statusCode":404},{"date":"2021-07-01T04:52:05.890Z","success":true,"statusCode":200},{"date":"2021-07-01T05:11:20.970Z","success":true,"statusCode":200},{"date":"2021-07-01T05:28:00.760Z","success":true,"statusCode":200},{"date":"2021-07-01T05:37:36.416Z","success":true,"statusCode":200},{"date":"2021-07-01T05:47:16.943Z","success":true,"statusCode":200},{"date":"2021-07-01T05:57:02.956Z","success":true,"statusCode":200},{"date":"2021-07-01T06:24:34.609Z","success":true,"statusCode":200},{"date":"2021-07-01T06:51:21.025Z","success":true,"statusCode":200},{"date":"2021-07-01T07:11:58.913Z","success":true,"statusCode":200},{"date":"2021-07-01T07:28:47.656Z","success":true,"statusCode":200},{"date":"2021-07-01T07:38:36.732Z","success":true,"statusCode":200},{"date":"2021-07-01T07:48:12.731Z","success":true,"statusCode":200},{"date":"2021-07-01T07:57:59.545Z","success":true,"statusCode":200},{"date":"2021-07-01T08:21:56.316Z","success":true,"statusCode":200},{"date":"2021-07-01T08:40:14.438Z","success":true,"statusCode":200},{"date":"2021-07-01T08:49:53.365Z","success":true,"statusCode":200},{"date":"2021-07-01T08:59:45.933Z","success":true,"statusCode":200},{"date":"2021-07-01T09:25:04.427Z","success":true,"statusCode":200},{"date":"2021-07-01T09:41:18.989Z","success":true,"statusCode":200},{"date":"2021-07-01T09:54:50.218Z","success":true,"statusCode":200},{"date":"2021-07-01T10:14:20.963Z","success":true,"statusCode":200},{"date":"2021-07-01T10:34:59.293Z","success":true,"statusCode":200},{"date":"2021-07-01T10:45:55.747Z","success":true,"statusCode":200},{"date":"2021-07-01T10:55:30.007Z","success":true,"statusCode":200},{"date":"2021-07-01T11:11:10.325Z","success":true,"statusCode":200},{"date":"2021-07-01T11:27:12.468Z","success":true,"statusCode":200},{"date":"2021-07-01T11:36:56.391Z","success":true,"statusCode":200},{"date":"2021-07-01T11:46:34.627Z","success":true,"statusCode":200},{"date":"2021-07-01T11:56:24.701Z","success":true,"statusCode":200}]