[{"date":"2021-03-24T00:34:38.306Z","success":true,"statusCode":200},{"date":"2021-03-24T01:34:16.702Z","success":true,"statusCode":200},{"date":"2021-03-24T02:21:07.602Z","success":true,"statusCode":200},{"date":"2021-03-24T02:56:52.522Z","success":true,"statusCode":200},{"date":"2021-03-24T03:25:58.985Z","success":true,"statusCode":200},{"date":"2021-03-24T03:44:20.751Z","success":true,"statusCode":200},{"date":"2021-03-24T03:55:03.435Z","success":true,"statusCode":200},{"date":"2021-03-24T04:26:39.354Z","success":true,"statusCode":200},{"date":"2021-03-24T05:11:25.578Z","success":true,"statusCode":200},{"date":"2021-03-24T05:46:57.310Z","success":true,"statusCode":200},{"date":"2021-03-24T05:57:31.952Z","success":true,"statusCode":200},{"date":"2021-03-24T06:34:07.733Z","success":true,"statusCode":200},{"date":"2021-03-24T07:09:52.551Z","success":true,"statusCode":200},{"date":"2021-03-24T07:40:36.165Z","success":true,"statusCode":200},{"date":"2021-03-24T07:56:14.703Z","success":true,"statusCode":200},{"date":"2021-03-24T08:30:48.529Z","success":true,"statusCode":200},{"date":"2021-03-24T09:04:50.390Z","success":true,"statusCode":200},{"date":"2021-03-24T09:41:54.779Z","success":true,"statusCode":200},{"date":"2021-03-24T10:05:33.353Z","success":true,"statusCode":200},{"date":"2021-03-24T10:45:23.868Z","success":true,"statusCode":200},{"date":"2021-03-24T11:05:40.565Z","success":true,"statusCode":200}]